.DS_Store
README.md
setup.py
dist/voltage_imaging_analysis-0.1.0.tar.gz
dist/voltage_imaging_analysis-0.1.5.tar.gz
dist/voltage_imaging_analysis-0.1.6.tar.gz
voltage_imaging_analysis/__init__.py
voltage_imaging_analysis/test_1p_analysis.py
voltage_imaging_analysis/voltage_imaging_analysis_fcts.py
voltage_imaging_analysis.egg-info/PKG-INFO
voltage_imaging_analysis.egg-info/SOURCES.txt
voltage_imaging_analysis.egg-info/dependency_links.txt
voltage_imaging_analysis.egg-info/requires.txt
voltage_imaging_analysis.egg-info/top_level.txt
voltage_imaging_analysis/__pycache__/__init__.cpython-39.pyc