Metadata-Version: 2.1
Name: voltage-imaging-analysis
Version: 0.1.7
Summary: Python package used for analysing voltage imaging data.
Home-page: https://github.com/rrsims21/voltage_imaging_analysis/
Author: Ruth Sims
Author-email: ruth.sims@inserm.fr
License: BSD 2-clause
Platform: UNKNOWN
Classifier: Development Status :: 1 - Planning
Classifier: Intended Audience :: Science/Research
Classifier: License :: OSI Approved :: BSD License
Classifier: Programming Language :: Python :: 3.5
